wbx_workspaces/__init__.py
wbx_workspaces/__main__.py
wbx_workspaces/wbx.py
wbx_workspaces/wbx_dataframe.py
wbx_workspaces/wbx_utils.py
wbx_workspaces-1.3.2.dist-info/METADATA
wbx_workspaces-1.3.2.dist-info/WHEEL
wbx_workspaces-1.3.2.dist-info/licenses/LICENSE
wbx_workspaces-1.3.2.dist-info/RECORD
