Metadata-Version: 2.4
Name: wbx-workspaces
Version: 1.3.2
Summary: Commands to download Webex Workspaces stats
Author-email: Stephane Cohen <stecohen@gmail.com>
License: MIT License
License-File: LICENSE
Keywords: Compliance,Control Hub,Webex
Classifier: License :: OSI Approved :: MIT License
Classifier: Programming Language :: Python
Classifier: Programming Language :: Python :: 3
Requires-Python: >=3.10
Requires-Dist: click
Requires-Dist: pandas
Requires-Dist: requests
